LICENSE
README.md
setup.py
aea/__init__.py
aea/aea.py
aea/murmur.py
python_aea.egg-info/PKG-INFO
python_aea.egg-info/SOURCES.txt
python_aea.egg-info/dependency_links.txt
python_aea.egg-info/requires.txt
python_aea.egg-info/top_level.txt
tests/test_aea.py